setup.py
mplstyle/__init__.py
mplstyle/api.py
mplstyle/dotify.py
mplstyle.egg-info/PKG-INFO
mplstyle.egg-info/SOURCES.txt
mplstyle.egg-info/dependency_links.txt
mplstyle.egg-info/top_level.txt
mplstyle/styles/__init__.py
mplstyle/styles/simple.py