Metadata-Version: 1.0
Name: mplstyle
Version: 0.1.1
Summary: A simple API for setting matplotlib styles in matplotlib.
Home-page: https://github.com/jsvine/mplstyle
Author: Jeremy Singer-Vine
Author-email: jsvine@gmail.com
License: MIT
Platform: UNKNOWN
Classifier: Development Status :: 4 - Beta
Classifier: Intended Audience :: Developers
Classifier: Intended Audience :: Science/Research
Classifier: License :: OSI Approved :: MIT License
Classifier: Natural Language :: English
Classifier: Operating System :: OS Independent
Classifier: Programming Language :: Python
Classifier: Programming Language :: Python :: 2
Classifier: Topic :: Scientific/Engineering :: Visualization
